archivist_samples/__init__.py
archivist_samples/about.py
archivist_samples/archivist.py
archivist_samples/constants.py
archivist_samples/c2pa/__init__.py
archivist_samples/c2pa/__main__.py
archivist_samples/c2pa/c2pa.py
archivist_samples/c2pa/main.py
archivist_samples/c2pa/run.py
archivist_samples/c2pa/c2pa_files/__init__.py
archivist_samples/c2pa/c2pa_files/detailed.json
archivist_samples/c2pa/c2pa_files/edited_signed_image.c2pa
archivist_samples/c2pa/c2pa_files/image.jpg
archivist_samples/c2pa/c2pa_files/info.txt
archivist_samples/c2pa/c2pa_files/ingredient.json
archivist_samples/c2pa/c2pa_files/manifest_store.json
archivist_samples/c2pa/c2pa_files/parent_signed_image.c2pa
archivist_samples/c2pa/c2pa_files/signed_image.c2pa
archivist_samples/c2pa/c2pa_files/signed_image.jpg
archivist_samples/document/__init__.py
archivist_samples/document/__main__.py
archivist_samples/document/document.py
archivist_samples/document/main.py
archivist_samples/document/run.py
archivist_samples/document/document_files/AsteroidMiningIncDiscount.pdf
archivist_samples/document/document_files/AsteroidMiningIncOrderNumber.pdf
archivist_samples/document/document_files/AsteroidMiningIncOriginalInvoice.pdf
archivist_samples/document/document_files/DocumentPrimaryImage.jpg
archivist_samples/document/document_files/__init__.py
archivist_samples/door_entry/__init__.py
archivist_samples/door_entry/__main__.py
archivist_samples/door_entry/main.py
archivist_samples/door_entry/run.py
archivist_samples/door_entry/images/__init__.py
archivist_samples/door_entry/images/assets/__init__.py
archivist_samples/door_entry/images/assets/bastille.jpg
archivist_samples/door_entry/images/assets/cityhall.jpg
archivist_samples/door_entry/images/assets/courts.jpg
archivist_samples/door_entry/images/assets/entry_terminal.jpg
archivist_samples/door_entry/images/assets/gdn_front.jpg
archivist_samples/door_entry/images/assets/gdn_side.jpg
archivist_samples/door_entry/images/assets/smartcard.jpg
datatrails_samples-0.20.0.dist-info/licenses/LICENSE
datatrails_samples-0.20.0.dist-info/METADATA
datatrails_samples-0.20.0.dist-info/WHEEL
datatrails_samples-0.20.0.dist-info/entry_points.txt
datatrails_samples-0.20.0.dist-info/top_level.txt
datatrails_samples-0.20.0.dist-info/RECORD
