Metadata-Version: 2.4
Name: datatrails-samples
Version: 0.20.0
Summary: DataTrails Examples
Home-page: https://github.com/datatrails/datatrails-samples
Author: DataTrails Inc.
Author-email: support@datatrails.ai
License: MIT
Project-URL: Source, https://github.com/datatrails/datatrails-samples
Project-URL: Tracker, https://github.com/datatrails/datatrails-samples/issues
Classifier: Development Status :: 3 - Alpha
Classifier: Environment :: Console
Classifier: Intended Audience :: Developers
Classifier: License :: OSI Approved :: MIT License
Classifier: Operating System :: POSIX :: Linux
Classifier: Programming Language :: Python :: 3.9
Classifier: Topic :: Utilities
Requires-Python: >=3.9
License-File: LICENSE
Requires-Dist: cryptography~=41.0.2
Requires-Dist: pyyaml~=6.0.1
Requires-Dist: datatrails-archivist==0.35.0
Dynamic: license-file
